README.rst
indenti.py
setup.py
indenti.egg-info/PKG-INFO
indenti.egg-info/SOURCES.txt
indenti.egg-info/dependency_links.txt
indenti.egg-info/entry_points.txt
indenti.egg-info/top_level.txt