Metadata-Version: 1.1
Name: indenti
Version: 1.4
Summary: Tools for building strings, XML/HTML markup, and other indented text.
Home-page: https://github.com/lainproliant/indent-tools
Author: Lain Supe (lainproliant)
Author-email: lainproliant@gmail.com
License: MIT
Keywords: indent text formatting xml html
Platform: UNKNOWN
Classifier: Development Status :: 4 - Beta
Classifier: Intended Audience :: Developers
Classifier: License :: OSI Approved :: MIT License
Classifier: Programming Language :: Python :: 3
Classifier: Programming Language :: Python :: 3.2
Classifier: Programming Language :: Python :: 3.3
Classifier: Programming Language :: Python :: 3.4
Classifier: Programming Language :: Python :: 3.5
